baresquare_aws_py/__init__.py
baresquare_aws_py/authentication.py
baresquare_aws_py/s3.py
baresquare_aws_py/ssm.py
baresquare_aws_py-0.1.16.dist-info/METADATA
baresquare_aws_py-0.1.16.dist-info/WHEEL
baresquare_aws_py-0.1.16.dist-info/RECORD
