Metadata-Version: 2.4
Name: baresquare-aws-py
Version: 0.1.16
Summary: Baresquare's AWS Python utilities
License-Expression: MIT
Requires-Python: >=3.12
Requires-Dist: baresquare-core-py>=0.1.16
Requires-Dist: boto3>=1.38.21
Requires-Dist: pyjwt[crypto]==2.10.1
Requires-Dist: requests==2.32.3
Provides-Extra: linting
Requires-Dist: ruff==0.11.9; extra == 'linting'
Provides-Extra: testing
Requires-Dist: pytest==8.3.5; extra == 'testing'
